CHANGELOG.md
plasted-1.0.0.dist-info/METADATA
plasted-1.0.0.dist-info/WHEEL
plasted-1.0.0.dist-info/entry_points.txt
plasted/__init__.py
plasted/py.typed
plasted-1.0.0.dist-info/RECORD
