Metadata-Version: 2.1
Name: plasted
Version: 1.0.0
Summary: A WSGI app maded from a PLASTER_URI environment variable.
Author-Email: Guillaume Gauvrit <guillaume@gauvr.it>
Project-URL: Homepage, https://github.com/mardiros/plasted
Project-URL: Documentation, https://github.com/mardiros/plasted/blob/main/README.md
Project-URL: Repository, https://github.com/mardiros/plasted.git
Project-URL: Issues, https://github.com/mardiros/plasted/issues
Project-URL: Changelog, https://github.com/mardiros/plasted/blob/main/CHANGELOG.md
Requires-Python: >=3.9
Requires-Dist: plaster<2,>=1.1.2
